pica_ai/__init__.py
pica_ai/client.py
pica_ai/logger.py
pica_ai/models.py
pica_ai/prompts.py
pica_ai-1.0.0.dist-info/licenses/LICENSE
tests/__init__.py
tests/test_client.py
pica_ai-1.0.0.dist-info/METADATA
pica_ai-1.0.0.dist-info/WHEEL
pica_ai-1.0.0.dist-info/top_level.txt
pica_ai-1.0.0.dist-info/RECORD
