Metadata-Version: 2.4
Name: pica-ai
Version: 1.0.0
Summary: Client for interacting with the Pica API
Home-page: https://github.com/picahq/pica-ai
Author: Pica
Author-email: support@picaos.com
Classifier: Programming Language :: Python :: 3
Classifier: License :: OSI Approved :: GNU General Public License v3 (GPLv3)
Classifier: Operating System :: OS Independent
Requires-Python: >=3.7
License-File: LICENSE
Requires-Dist: requests==2.32.3
Requires-Dist: requests-toolbelt==1.0.0
Requires-Dist: pydantic==2.11.1
Requires-Dist: pytest==8.3.5
Dynamic: author
Dynamic: author-email
Dynamic: classifier
Dynamic: description
Dynamic: description-content-type
Dynamic: home-page
Dynamic: license-file
Dynamic: requires-dist
Dynamic: requires-python
Dynamic: summary
